CHANGELOG.md
LICENSE
MANIFEST.in
README.md
requirements.txt
setup.py
ampapi/__init__.py
ampapi/ads.py
ampapi/adsmodule.py
ampapi/analytics.py
ampapi/base.py
ampapi/bridge.py
ampapi/core.py
ampapi/emailsender.py
ampapi/filebackup.py
ampapi/filemanager.py
ampapi/instance.py
ampapi/minecraft.py
ampapi/types.py
ampapi/util.py
cubecoders_amp_api_wrapper.egg-info/PKG-INFO
cubecoders_amp_api_wrapper.egg-info/SOURCES.txt
cubecoders_amp_api_wrapper.egg-info/dependency_links.txt
cubecoders_amp_api_wrapper.egg-info/requires.txt
cubecoders_amp_api_wrapper.egg-info/top_level.txt
docs/ADS_api_spec.md
docs/Minecraft_api_spec.md
docs/permission_nodes.md
docs/permission_nodes.txt
docs/setting_nodes.md
docs/setting_nodes.txt